drever/__init__.py
drever/base_class.py
drever/bypass.py
drever/pkg_info.py
drever/stream_filter.py
drever/video_filter.py
drever/data_handlers/__init__.py
drever/data_handlers/image.py
drever/data_handlers/stream.py
drever/vhdl/data_handlers/image_data_pkg.vhd
drever/vhdl/data_handlers/stream_data_pkg.vhd
drever-0.0.9.dist-info/METADATA
drever-0.0.9.dist-info/WHEEL
drever-0.0.9.dist-info/top_level.txt
drever-0.0.9.dist-info/RECORD
