Metadata-Version: 2.1
Name: drever
Version: 0.0.9
Summary: A framework for handling testvectors within an HDL testbench.
Home-page: https://gitlab.com/Elpra/drever-framework/drever
Author: Tobias Baumann
Author-email: tobias.baumann@elpra.de
License: UNKNOWN
Platform: UNKNOWN
Classifier: Programming Language :: Python :: 3
Classifier: Development Status :: 3 - Alpha
Classifier: License :: OSI Approved :: GNU General Public License v3 or later (GPLv3+)
Classifier: Operating System :: OS Independent
Requires-Dist: vunit-hdl
Requires-Dist: numpy
Requires-Dist: tabulate
Requires-Dist: pandas
